[
  {
    "nameWithOwner": "perditioinc/codecompanion.nvim",
    "name": "codecompanion.nvim",
    "description": "\u2728 AI Coding, Vim Style",
    "stars": 0,
    "forks": 0,
    "primaryLanguage": "Lua",
    "pushedAt": "2026-04-06T19:57:48Z",
    "updatedAt": "2026-04-07T00:25:50Z",
    "createdAt": "2026-04-07T00:25:49Z",
    "isArchived": false,
    "isFork": true,
    "isEmpty": false,
    "topics": [],
    "licenseName": "Apache License 2.0",
    "openIssues": 0,
    "defaultBranch": "main",
    "parentRepo": "olimorris/codecompanion.nvim",
    "parentStars": 6702,
    "parentForks": 429,
    "isPrivate": false
  }
]